Workbook
Name aporte: APP!$D$17
Name patrimonio: APP!$D$20
Name qtd_anos: APP!$D$18
Name rendimento_carteira: APP!$D$13
Name salario: APP!$D$12
Name sugestao_investimento: APP!$D$14
Name taxa_mensal: APP!$D$19

Sheet APP
B11: CONFIGURAÇÕES
B12: Salário | D12: 2000
B13: Rendimento Carteira | D13: 0.006
B14: Sugestão de Investimento | C14: 0.3 | D14: =salario*C14 -> 600
B16: INVESTIMENTO MENSAL
B17: Quanto investir por mês? | D17: 200
B18: Por quantos anos? | D18: 5
B19: Taxa de rendimento mensal? | D19: 0.01079
B20: Patrimônio acumulado | D20: =FV(taxa_mensal,qtd_anos*12,aporte*-1) -> 16755.383
B21: Total aportado | D21: =aporte*12*qtd_anos -> 12000
B22: Ganho acumulado | D22: =patrimonio-D21 -> 4755.3828
B23: Dividendos mensais | D23: =patrimonio*rendimento_carteira -> 100.5323
B25: CENÁRIOS | C25: PATRIMÔNIO | D25: DIVIDENDOS
A26: 2 | B26: Quanto em 2 anos? | C26: =FV($D$19,$A26*12,$D$17*-1) -> 5445.5255 | D26: =C26*rendimento_carteira -> 32.673153
A27: 5 | B27: Quanto em 5 anos? | C27: =FV($D$19,$A27*12,$D$17*-1) -> 16755.383 | D27: =C27*rendimento_carteira -> 100.5323
A28: 10 | B28: Quanto em 10 anos? | C28: =FV($D$19,$A28*12,$D$17*-1) -> 48656.843 | D28: =C28*rendimento_carteira -> 291.94106
A29: 20 | B29: Quanto em 20 anos? | C29: =FV($D$19,$A29*12,$D$17*-1) -> 225039.68 | D29: =C29*rendimento_carteira -> 1350.2381
A30: 30 | B30: Quanto em 30 anos? | C30: =FV($D$19,$A30*12,$D$17*-1) -> 864433.93 | D30: =C30*rendimento_carteira -> 5186.6036
C32: Filtre seu perfil de investidor abaixo
B33: PERFIL | C33: Moderado
B34: VALOR A SER INVESTIDO POR MÊS | C34: =aporte -> 200
B36: TIPO DE FII | C36: Percentual Sugerido | D36: Valores
B37: PAPEL | C37: =VLOOKUP($C$33&"-"&B37,tbl_apoio!$A:$D,4,FALSE) -> 0.32 | D37: =C37*$C$34 -> 64
B38: TIJOLO | C38: =VLOOKUP($C$33&"-"&B38,tbl_apoio!$A:$D,4,FALSE) -> 0.35 | D38: =C38*$C$34 -> 70
B39: HÍBRIDOS | C39: =VLOOKUP($C$33&"-"&B39,tbl_apoio!$A:$D,4,FALSE) -> 0.08 | D39: =C39*$C$34 -> 16
B40: FOFs | C40: =VLOOKUP($C$33&"-"&B40,tbl_apoio!$A:$D,4,FALSE) -> 0.05 | D40: =C40*$C$34 -> 10
B41: DESENVOLVIMENTO | C41: =VLOOKUP($C$33&"-"&B41,tbl_apoio!$A:$D,4,FALSE) -> 0.1 | D41: =C41*$C$34 -> 20
B42: HOTELARIAS | C42: =VLOOKUP($C$33&"-"&B42,tbl_apoio!$A:$D,4,FALSE) -> 0.1 | D42: =C42*$C$34 -> 20
D43: =SUM(D37:D42) -> 200
B66: Observação: Simulação educacional baseada em taxas constantes; resultados não representam garantia de rentabilidade

Sheet tbl_apoio
A2: CHAVE COMPOSTA | B2: PERFIL | C2: TIPO DE FII | D2: %
A3: =B3&"-"&C3 -> Conservador-PAPEL | B3: Conservador | C3: PAPEL | D3: 0.3
A4: =B4&"-"&C4 -> Conservador-TIJOLO | B4: Conservador | C4: TIJOLO | D4: 0.5
A5: =B5&"-"&C5 -> Conservador-HÍBRIDOS | B5: Conservador | C5: HÍBRIDOS | D5: 0.1
A6: =B6&"-"&C6 -> Conservador-FOFs | B6: Conservador | C6: FOFs | D6: 0.1
A7: =B7&"-"&C7 -> Conservador-DESENVOLVIMENTO | B7: Conservador | C7: DESENVOLVIMENTO | D7: 0
A8: =B8&"-"&C8 -> Conservador-HOTELARIAS | B8: Conservador | C8: HOTELARIAS | D8: 0
A9: =B9&"-"&C9 -> Moderado-PAPEL | B9: Moderado | C9: PAPEL | D9: 0.32
A10: =B10&"-"&C10 -> Moderado-TIJOLO | B10: Moderado | C10: TIJOLO | D10: 0.35
A11: =B11&"-"&C11 -> Moderado-HÍBRIDOS | B11: Moderado | C11: HÍBRIDOS | D11: 0.08
A12: =B12&"-"&C12 -> Moderado-FOFs | B12: Moderado | C12: FOFs | D12: 0.05
A13: =B13&"-"&C13 -> Moderado-DESENVOLVIMENTO | B13: Moderado | C13: DESENVOLVIMENTO | D13: 0.1
A14: =B14&"-"&C14 -> Moderado-HOTELARIAS | B14: Moderado | C14: HOTELARIAS | D14: 0.1
... A20: =B20&"-"&C20 -> Agressivo-HOTELARIAS | B20: Agressivo | C20: HOTELARIAS | D20: 0.1
